db_utils/__init__.py
db_utils/main.py
db_utils_paladinxb-0.1.0.dist-info/METADATA
db_utils_paladinxb-0.1.0.dist-info/WHEEL
db_utils_paladinxb-0.1.0.dist-info/top_level.txt
db_utils_paladinxb-0.1.0.dist-info/RECORD
